sphinxcontrib_svgbob-0.3.1.dist-info/METADATA
sphinxcontrib_svgbob-0.3.1.dist-info/RECORD
sphinxcontrib_svgbob-0.3.1.dist-info/WHEEL
sphinxcontrib_svgbob-0.3.1.dist-info/licenses/COPYING
sphinxcontrib/svgbob/transform.py
sphinxcontrib/svgbob/directive.py
sphinxcontrib/svgbob/_svgbob.cpython-313-aarch64-linux-gnu.so
sphinxcontrib/svgbob/_svgbob.pyi
sphinxcontrib/svgbob/py.typed
sphinxcontrib/svgbob/__init__.py
sphinxcontrib/svgbob/node.py
sphinxcontrib/svgbob/tests/test_svgbob.py
sphinxcontrib/svgbob/tests/__init__.py
sphinxcontrib/svgbob/tests/test_sphinx.py
sphinxcontrib/svgbob/_svgbob/README.md
sphinxcontrib/svgbob/_svgbob/Cargo.lock
sphinxcontrib/svgbob/_svgbob/lib.rs
sphinxcontrib/svgbob/_svgbob/Cargo.toml
sphinxcontrib/svgbob/_svgbob/build.rs
sphinxcontrib/svgbob/_svgbob/built.rs
