Metadata-Version: 2.4
Name: sphinxcontrib-svgbob
Version: 0.3.1
Classifier: Development Status :: 4 - Beta
Classifier: Framework :: Sphinx :: Extension
Classifier: Intended Audience :: Developers
Classifier: License :: OSI Approved :: MIT License
Classifier: Operating System :: OS Independent
Classifier: Programming Language :: Python
Classifier: Programming Language :: Python :: 3.8
Classifier: Programming Language :: Python :: 3.9
Classifier: Programming Language :: Python :: 3.10
Classifier: Programming Language :: Python :: 3.11
Classifier: Programming Language :: Python :: 3.12
Classifier: Programming Language :: Python :: 3.13
Classifier: Programming Language :: Rust
Classifier: Topic :: Documentation :: Sphinx
Classifier: Topic :: Software Development :: Documentation
Classifier: Topic :: Text Processing
Classifier: Typing :: Typed
Requires-Dist: sphinx
License-File: COPYING
Summary: A Sphinx extension to convert ASCII diagrams to SVGs with Svgbob.
Keywords: sphinx,documentation,svg,diagram,ascii
Home-Page: https://pypi.org/projects/sphinxcontrib-svgbob
Author: Martin Larralde <martin.larralde@embl.de>
Author-email: Martin Larralde <martin.larralde@embl.de>
License: MIT
Requires-Python: >=3.7
Project-URL: Bug Tracker, https://github.com/sphinx-contrib/svgbob/issues
Project-URL: Changelog, https://github.com/sphinx-contrib/svgbob/blob/master/CHANGELOG.md
Project-URL: PyPI, https://pypi.org/project/sphinxcontrib-svgbob
